pfo/__init__.py
pfo/pf/__init__.py
pfo/pf/mc.py
pfo/pf/portfolio.py
pfo/pf/valuations.py
pfo/stocks/__init__.py
pfo/stocks/cluster.py
pfo/stocks/returns.py
pfo/stocks/stock.py
pfo/utils/__init__.py
pfo/utils/data_utils.py
pfo/utils/market_data.py
pfo/utils/moex.py
pfo-0.0.8.dist-info/LICENSE
pfo-0.0.8.dist-info/METADATA
pfo-0.0.8.dist-info/WHEEL
pfo-0.0.8.dist-info/top_level.txt
pfo-0.0.8.dist-info/RECORD
