Metadata-Version: 2.1
Name: pfo
Version: 0.0.8
Summary: A package to analyse personal investments
Home-page: https://github.com/neverbreaks/pfo
Author: shurajan
Author-email: neverbreaks2020@gmail.com
License: UNKNOWN
Platform: UNKNOWN
Classifier: Programming Language :: Python :: 3.8
Classifier: License :: OSI Approved :: MIT License
Requires-Dist: numpy (==1.19.3)
Requires-Dist: yfinance (>=0.1.55)
Requires-Dist: pandas (==1.1.4)
Requires-Dist: apimoex (>=1.2.0)
Requires-Dist: scikit-learn (>=0.23.2)
Requires-Dist: tqdm (>=4.53.0)
